esnodepy/__init__.py
esnodepy/cli.py
esnodepy/engine/boundaries.py
esnodepy/engine/graph.py
esnodepy/engine/report.py
esnodepy/scanners/diff.py
esnodepy/scanners/imports.py
esnodepy/scanners/runtime.py
esnodepy/scanners/scan.py
esnodepy-0.2.1.dist-info/licenses/LICENSE
esnodepy-0.2.1.dist-info/METADATA
esnodepy-0.2.1.dist-info/WHEEL
esnodepy-0.2.1.dist-info/entry_points.txt
esnodepy-0.2.1.dist-info/top_level.txt
esnodepy-0.2.1.dist-info/RECORD
