Metadata-Version: 2.4
Name: esnodePy
Version: 0.2.1
Summary: Zero-config Python boundary intelligence
Author-email: ESNODE <info@esnode.co>
License: ESNODE COMMUNITY LICENSE 1.0
Project-URL: Homepage, https://github.com/ESNODE/esnodePy
Project-URL: Bug Tracker, https://github.com/ESNODE/esnodePy/issues
Classifier: Development Status :: 3 - Alpha
Classifier: Intended Audience :: Developers
Classifier: License :: Other/Proprietary License
Classifier: Programming Language :: Python :: 3
Requires-Python: >=3.9
License-File: LICENSE
Provides-Extra: dev
Requires-Dist: pytest; extra == "dev"
Requires-Dist: pytest-cov; extra == "dev"
Requires-Dist: black; extra == "dev"
Requires-Dist: isort; extra == "dev"
Requires-Dist: mypy; extra == "dev"
Dynamic: license-file
